stpsf/__init__.py
stpsf/conftest.py
stpsf/constants.py
stpsf/detectors.py
stpsf/distortion.py
stpsf/gridded_library.py
stpsf/mast_wss.py
stpsf/match_data.py
stpsf/notes_new.txt
stpsf/opds.py
stpsf/optical_budget.py
stpsf/optics.py
stpsf/roman.py
stpsf/stpsf_core.py
stpsf/surs.py
stpsf/trending.py
stpsf/utils.py
stpsf/version.py
stpsf/otelm/JWST_influence_functions_control_with_sm.fits
stpsf/otelm/NIRCam_WL_Empirical_Power.csv
stpsf/otelm/README.txt
stpsf/otelm/SMIF_hexike.csv
stpsf/otelm/__init__.py
stpsf/otelm/coarse_track1_sim_pointing.fits
stpsf/otelm/coarse_track2_sim_pointing.fits
stpsf/otelm/jwst_wfe_summary_from_optical_budget.csv
stpsf/otelm/seg_sens.txt
stpsf/otelm/thermal_OPD_fitting_parameters_9H_um.fits
stpsf/tests/README.txt
stpsf/tests/__init__.py
stpsf/tests/test_detectors.py
stpsf/tests/test_distortion.py
stpsf/tests/test_errorhandling.py
stpsf/tests/test_fgs.py
stpsf/tests/test_jitter.py
stpsf/tests/test_mast_wss.py
stpsf/tests/test_miri.py
stpsf/tests/test_nircam.py
stpsf/tests/test_niriss.py
stpsf/tests/test_nirspec.py
stpsf/tests/test_opds.py
stpsf/tests/test_optical_budget.py
stpsf/tests/test_psfgrid.py
stpsf/tests/test_roman.py
stpsf/tests/test_stpsf.py
stpsf/tests/test_trending.py
stpsf/tests/test_utils.py
stpsf/tests/surs/__init__.py
stpsf/tests/surs/example_alldof_A1-SM_sur.xml
stpsf/tests/surs/example_coarse_phasing_N2019041204_sur.xml
stpsf/tests/surs/example_fine_phasing_R201902010S_sur.xml
stpsf/tests/surs/example_global_alignment_N201902010F_sur.xml
stpsf/tests/surs/example_image_stacking_O201904110E_sur.xml
stpsf-2.1.0.dist-info/licenses/LICENSE.md
stpsf-2.1.0.dist-info/METADATA
stpsf-2.1.0.dist-info/WHEEL
stpsf-2.1.0.dist-info/top_level.txt
stpsf-2.1.0.dist-info/RECORD
