Metadata-Version: 2.4
Name: stpsf
Version: 2.1.0
Summary: Creates simulated point spread functions for Space Telescopes (James Webb, Roman)
Author-email: Association of Universities for Research in Astronomy <help@stsci.edu>
Project-URL: Homepage, http://stpsf.readthedocs.io/
Project-URL: github_project, https://github.com/spacetelescope/stpsf
Requires-Python: >=3.10
License-File: LICENSE.md
Requires-Dist: numpy>=1.21.6
Requires-Dist: scipy>=1.5.0
Requires-Dist: matplotlib>=3.2.0
Requires-Dist: astropy>=5.1.0
Requires-Dist: photutils>=1.10.0
Requires-Dist: poppy>=1.0.0
Requires-Dist: pysiaf>=0.23.3
Requires-Dist: synphot>=1.0.0
Requires-Dist: astroquery>=0.4.6
Provides-Extra: test
Requires-Dist: pytest; extra == "test"
Requires-Dist: pytest-astropy; extra == "test"
Provides-Extra: docs
Requires-Dist: nbsphinx; extra == "docs"
Requires-Dist: sphinx; extra == "docs"
Requires-Dist: stsci_rtd_theme; extra == "docs"
Requires-Dist: sphinx-astropy; extra == "docs"
Requires-Dist: sphinx-automodapi; extra == "docs"
Requires-Dist: sphinx-issues; extra == "docs"
Requires-Dist: tomli; python_version < "3.11" and extra == "docs"
Dynamic: license-file
